weather_command/__init__.py
weather_command/__main__.py
weather_command/_builder.py
weather_command/_cache.py
weather_command/_config.py
weather_command/_location.py
weather_command/_utils.py
weather_command/_weather.py
weather_command/errors.py
weather_command/main.py
weather_command/models/__init__.py
weather_command/models/location.py
weather_command/models/weather.py
weather_command/py.typed
weather_command/settings_commands.py
weather_command-6.1.7.dist-info/LICENSE
weather_command-6.1.7.dist-info/METADATA
weather_command-6.1.7.dist-info/WHEEL
weather_command-6.1.7.dist-info/entry_points.txt
weather_command-6.1.7.dist-info/RECORD
