Metadata-Version: 2.1
Name: weather-command
Version: 6.1.7
Summary: Command line weather app
Home-page: https://github.com/sanders41/weather-command
License: MIT
Keywords: weather,cli
Author: Paul Sanders
Author-email: psanders1@gmail.com
Requires-Python: >=3.8,<4.0
Classifier: Development Status :: 7 - Inactive
Classifier: License :: OSI Approved :: MIT License
Classifier: Programming Language :: Python :: 3
Classifier: Programming Language :: Python :: 3.8
Classifier: Programming Language :: Python :: 3.9
Classifier: Programming Language :: Python :: 3.10
Classifier: Programming Language :: Python :: 3.11
Classifier: Programming Language :: Python :: 3.12
Requires-Dist: camel-converter[pydantic] (==3.1.2)
Requires-Dist: httpx (==0.27.2)
Requires-Dist: pydantic (==2.9.2)
Requires-Dist: pyyaml (==6.0.2)
Requires-Dist: rich (==13.9.2)
Requires-Dist: tenacity (==9.0.0)
Requires-Dist: typer (==0.12.5)
Project-URL: Documentation, https://github.com/sanders41/weather-command
Project-URL: Repository, https://github.com/sanders41/weather-command
